[
    {
        "name": "連音攻撃",
        "description": "プリセット",
        "data": {
            "selectedMotions": [
                "連音攻撃1段目",
                "連音攻撃2段目"
            ]
        }
    },
    {
        "name": "叩きつけ",
        "description": "プリセット",
        "data": {
            "selectedMotions": [
                "叩きつけ1段目",
                "叩きつけ2段目"
            ]
        }
    },
    {
        "name": "通常演奏",
        "description": "プリセット",
        "data": {
            "selectedMotions": [
                "演奏",
                "演奏衝撃波",
                "旋律発動時衝撃波"
            ]
        }
    },
    {
        "name": "通常演奏→重ね掛け",
        "description": "プリセット",
        "data": {
            "selectedMotions": [
                "演奏",
                "演奏衝撃波",
                "旋律発動時衝撃波",
                "重ね掛け1段目",
                "重ね掛け2段目_タイミングOK",
                "旋律発動時衝撃波"
            ]
        }
    },
    {
        "name": "通常演奏/奏撃3回→重ね掛け",
        "description": "プリセット",
        "data": {
            "selectedMotions": [
                "演奏",
                "演奏衝撃波",
                "旋律発動時衝撃波",
                "奏撃1_タイミングOK",
                "演奏衝撃波",
                "旋律発動時衝撃波",
                "奏撃2_タイミングOK",
                "演奏衝撃波",
                "旋律発動時衝撃波",
                "重ね掛け1段目",
                "重ね掛け2段目_タイミングOK",
                "旋律発動時衝撃波",
                "重ね掛け特殊衝撃波",
                "重ね掛け特殊衝撃波"
            ]
        }
    },
    {
        "name": "響周波【打】演奏",
        "description": "プリセット",
        "data": {
            "selectedMotions": [
                "演奏",
                "演奏衝撃波",
                "響周波【打】"
            ]
        }
    },
    {
        "name": "響周波【斬】演奏",
        "description": "プリセット",
        "data": {
            "selectedMotions": [
                "演奏",
                "演奏衝撃波",
                "響周波【斬】"
            ]
        }
    },
    {
        "name": "響周波【属性】演奏",
        "description": "プリセット",
        "data": {
            "selectedMotions": [
                "演奏",
                "演奏衝撃波",
                "響周波【斬】"
            ]
        }
    },
    {
        "name": "響周波【異常】演奏",
        "description": "プリセット",
        "data": {
            "selectedMotions": [
                "演奏",
                "演奏衝撃波",
                "響周波【異常】"
            ]
        }
    },
    {
        "name": "響玉→響周波【打】→重ね掛け",
        "description": "プリセット",
        "data": {
            "selectedMotions": [
                "響玉設置",
                "演奏",
                "演奏衝撃波",
                "響周波【打】",
                "響玉追撃_旋律",
                "重ね掛け1段目",
                "重ね掛け2段目_タイミングOK",
                "響周波【打】",
                "響玉追撃_旋律"
            ]
        }
    },
    {
        "name": "響玉→響周波【斬】→重ね掛け",
        "description": "プリセット",
        "data": {
            "selectedMotions": [
                "響玉設置",
                "演奏",
                "演奏衝撃波",
                "響周波【斬】",
                "響玉追撃_旋律",
                "重ね掛け1段目",
                "重ね掛け2段目_タイミングOK",
                "響周波【斬】",
                "響玉追撃_旋律"
            ]
        }
    },
    {
        "name": "響玉→響周波【属性】→重ね掛け",
        "description": "プリセット",
        "data": {
            "selectedMotions": [
                "響玉設置",
                "演奏",
                "演奏衝撃波",
                "響周波【属性】",
                "響玉追撃_旋律",
                "重ね掛け1段目",
                "重ね掛け2段目_タイミングOK",
                "響周波【属性】",
                "響玉追撃_旋律"
            ]
        }
    },
    {
        "name": "響玉→響周波【異常】→重ね掛け",
        "description": "プリセット",
        "data": {
            "selectedMotions": [
                "響玉設置",
                "演奏",
                "演奏衝撃波",
                "響周波【異常】",
                "響玉追撃_旋律",
                "重ね掛け1段目",
                "重ね掛け2段目_タイミングOK",
                "響周波【異常】",
                "響玉追撃_旋律"
            ]
        }
    },
    {
        "name": "弱点集中攻撃",
        "description": "プリセット",
        "data": {
            "selectedMotions": [
                "集中音撃【残響】突き",
                "集中音撃【残響】衝撃波",
                "集中音撃【残響】衝撃波",
                "集中音撃【残響】衝撃波",
                "集中音撃【残響】衝撃波",
                "集中音撃【残響】衝撃波",
                "集中音撃【残響】フィニッシュ"
            ]
        }
    },
    {
        "name": "響鳴の調べ_衝撃波2hit",
        "description": "プリセット",
        "data": {
            "selectedMotions": [
                "響鳴の調べ1段目",
                "響鳴の調べ2段目",
                "響鳴の調べ3段目",
                "響鳴の調べ衝撃波",
                "響鳴の調べ衝撃波"
            ]
        }
    }
]
